{"openapi":"3.1.0","info":{"title":"I-NERGY Load Forecasting Service API","description":"Collection of REST APIs for Serving Execution of I-NERGY Load Forecasting Service","license":{"name":"MIT","url":"https://opensource.org/licenses/MIT"},"version":"0.0.1"},"paths":{"/experimentation_pipeline/training/hyperparameter_entrypoints":{"get":{"tags":["Experimentation Pipeline"],"summary":"Get Experimentation Pipeline Hparam Entrypoints","operationId":"get_experimentation_pipeline_hparam_entrypoints_experimentation_pipeline_training_hyperparameter_entrypoints_get","responses":{"200":{"description":"Successful Response","content":{"application/json":{"schema":{}}}}}}},"/get_mlflow_tracking_uri":{"get":{"tags":["MLflow Info"],"summary":"Get Mlflow Tracking Uri","operationId":"get_mlflow_tracking_uri_get_mlflow_tracking_uri_get","responses":{"200":{"description":"Successful Response","content":{"application/json":{"schema":{}}}}}}},"/system_monitoring/get_cpu_usage":{"get":{"tags":["System Monitoring"],"summary":"Get Cpu Usage","operationId":"get_cpu_usage_system_monitoring_get_cpu_usage_get","responses":{"200":{"description":"Successful Response","content":{"application/json":{"schema":{}}}}}}},"/system_monitoring/get_memory_usage":{"get":{"tags":["System Monitoring"],"summary":"Get Memory Usage","operationId":"get_memory_usage_system_monitoring_get_memory_usage_get","responses":{"200":{"description":"Successful Response","content":{"application/json":{"schema":{}}}}}}},"/system_monitoring/get_gpu_usage":{"get":{"tags":["System Monitoring"],"summary":"Get Gpu Usage","operationId":"get_gpu_usage_system_monitoring_get_gpu_usage_get","responses":{"200":{"description":"Successful Response","content":{"application/json":{"schema":{}}}}}}},"/":{"get":{"summary":"Root","operationId":"root__get","responses":{"200":{"description":"Successful Response","content":{"application/json":{"schema":{}}}}}}},"/models/get_model_names/{resolution}/{multiple}":{"get":{"tags":["Metrics and models retrieval"],"summary":"Get Model Names","operationId":"get_model_names_models_get_model_names__resolution___multiple__get","parameters":[{"required":true,"schema":{"type":"integer","title":"Resolution"},"name":"resolution","in":"path"},{"required":true,"schema":{"type":"boolean","title":"Multiple"},"name":"multiple","in":"path"}],"responses":{"200":{"description":"Successful Response","content":{"application/json":{"schema":{}}}},"422":{"description":"Validation Error","content":{"application/json":{"schema":{"$ref":"#/components/schemas/HTTPValidationError"}}}}}}},"/upload/uploadCSVfile":{"post":{"tags":["Experimentation Pipeline"],"summary":"Create Upload Csv File","operationId":"create_upload_csv_file_upload_uploadCSVfile_post","requestBody":{"content":{"multipart/form-data":{"schema":{"$ref":"#/components/schemas/Body_create_upload_csv_file_upload_uploadCSVfile_post"}}},"required":true},"responses":{"200":{"description":"Successful Response","content":{"application/json":{"schema":{}}}},"422":{"description":"Validation Error","content":{"application/json":{"schema":{"$ref":"#/components/schemas/HTTPValidationError"}}}}}}},"/experimentation_pipeline/run_all":{"post":{"tags":["Experimentation Pipeline"],"summary":"Run Experimentation Pipeline","operationId":"run_experimentation_pipeline_experimentation_pipeline_run_all_post","requestBody":{"content":{"application/json":{"schema":{"type":"object","title":"Parameters"}}},"required":true},"responses":{"200":{"description":"Successful Response","content":{"application/json":{"schema":{}}}},"422":{"description":"Validation Error","content":{"application/json":{"schema":{"$ref":"#/components/schemas/HTTPValidationError"}}}}}}},"/metrics/get_metric_names":{"get":{"tags":["Metrics and models retrieval"],"summary":"Get Metric Names","operationId":"get_metric_names_metrics_get_metric_names_get","responses":{"200":{"description":"Successful Response","content":{"application/json":{"schema":{}}}}}}},"/results/get_list_of_experiments":{"get":{"tags":["MLflow Info","Model Evaluation"],"summary":"Get List Of Mlflow Experiments","operationId":"get_list_of_mlflow_experiments_results_get_list_of_experiments_get","responses":{"200":{"description":"Successful Response","content":{"application/json":{"schema":{}}}}}}},"/results/get_best_run_id_by_mlflow_experiment/{experiment_id}/{metric}":{"get":{"tags":["MLflow Info","Model Evaluation"],"summary":"Get Best Run Id By Mlflow Experiment","operationId":"get_best_run_id_by_mlflow_experiment_results_get_best_run_id_by_mlflow_experiment__experiment_id___metric__get","parameters":[{"required":true,"schema":{"type":"string","title":"Experiment Id"},"name":"experiment_id","in":"path"},{"required":true,"schema":{"type":"string","title":"Metric"},"name":"metric","in":"path"}],"responses":{"200":{"description":"Successful Response","content":{"application/json":{"schema":{}}}},"422":{"description":"Validation Error","content":{"application/json":{"schema":{"$ref":"#/components/schemas/HTTPValidationError"}}}}}}},"/results/get_forecast_vs_actual/{run_id}/n_samples/{n}":{"get":{"tags":["MLflow Info","Model Evaluation"],"summary":"Get Forecast Vs Actual","operationId":"get_forecast_vs_actual_results_get_forecast_vs_actual__run_id__n_samples__n__get","parameters":[{"required":true,"schema":{"type":"string","title":"Run Id"},"name":"run_id","in":"path"},{"required":true,"schema":{"type":"integer","title":"N"},"name":"n","in":"path"}],"responses":{"200":{"description":"Successful Response","content":{"application/json":{"schema":{}}}},"422":{"description":"Validation Error","content":{"application/json":{"schema":{"$ref":"#/components/schemas/HTTPValidationError"}}}}}}},"/results/get_metric_list/{run_id}":{"get":{"tags":["MLflow Info","Model Evaluation"],"summary":"Get Metric List","operationId":"get_metric_list_results_get_metric_list__run_id__get","parameters":[{"required":true,"schema":{"type":"string","title":"Run Id"},"name":"run_id","in":"path"}],"responses":{"200":{"description":"Successful Response","content":{"application/json":{"schema":{}}}},"422":{"description":"Validation Error","content":{"application/json":{"schema":{"$ref":"#/components/schemas/HTTPValidationError"}}}}}}}},"components":{"schemas":{"Body_create_upload_csv_file_upload_uploadCSVfile_post":{"properties":{"file":{"type":"string","format":"binary","title":"File"},"day_first":{"type":"boolean","title":"Day First","default":true},"multiple":{"type":"boolean","title":"Multiple","default":false}},"type":"object","required":["file"],"title":"Body_create_upload_csv_file_upload_uploadCSVfile_post"},"HTTPValidationError":{"properties":{"detail":{"items":{"$ref":"#/components/schemas/ValidationError"},"type":"array","title":"Detail"}},"type":"object","title":"HTTPValidationError"},"ValidationError":{"properties":{"loc":{"items":{"anyOf":[{"type":"string"},{"type":"integer"}]},"type":"array","title":"Location"},"msg":{"type":"string","title":"Message"},"type":{"type":"string","title":"Error Type"}},"type":"object","required":["loc","msg","type"],"title":"ValidationError"}}},"tags":[{"name":"MLflow Info","description":"REST APIs for retrieving elements from MLflow"},{"name":"Metrics and models retrieval","description":"REST APIs for retrieving available metrics, alongside models and their respective hyperparameters"},{"name":"Experimentation Pipeline","description":"REST APIs for setting up and running the experimentation pipeline"},{"name":"Model Evaluation","description":"REST APIs for retrieving model evaluation results"},{"name":"System Monitoring","description":"REST APIs for monitoring the host machine of the API"}]}
